Metadata-Version: 2.1
Name: rtspwebviewer
Version: 0.1.3
Summary: Simple web viewer for RTSP streams.
Home-page: https://github.com/luiscarlosgph/rtspwebviewer
Author: Luis C. Garcia-Peraza Herrera
Author-email: luiscarlos.gph@gmail.com
License: MIT
License-File: LICENSE
